Metadata-Version: 2.1
Name: odoo14-addon-github-connector-odoo
Version: 14.0.2.1.0
Summary: Analyze Odoo modules information from Github repositories
Home-page: https://github.com/OCA/interface-github
Author: Odoo Community Association (OCA), Sylvain LE GAL, GRAP
Author-email: support@odoo-community.org
License: AGPL-3
Platform: UNKNOWN
Classifier: Programming Language :: Python
Classifier: Framework :: Odoo
Classifier: Framework :: Odoo :: 14.0
Classifier: License :: OSI Approved :: GNU Affero General Public License v3
Requires-Python: >=3.6
Requires-Dist: odoo14-addon-github-connector
Requires-Dist: odoo (<14.1dev,>=14.0a)
Requires-Dist: pathspec
